tests/__init__.py
tests/main_test.py
wordlink/__init__.py
wordlink/__main__.py
wordlink-1.0.7.dist-info/LICENSE
wordlink-1.0.7.dist-info/METADATA
wordlink-1.0.7.dist-info/WHEEL
wordlink-1.0.7.dist-info/entry_points.txt
wordlink-1.0.7.dist-info/top_level.txt
wordlink-1.0.7.dist-info/RECORD
