Metadata-Version: 2.1
Name: wordlink
Version: 1.0.7
Summary: Word Link Generator
Home-page: https://github.com/psibir/wordlink
Download-URL: https://github.com/psibir/wordlink/archive/v_01.tar.gz
Author: Trevor Bloomfield
Author-email: bloomfieldtm@gmail.com
Keywords: word,link,html,console
Classifier: Programming Language :: Python :: 3
Classifier: License :: OSI Approved :: MIT License
Classifier: Operating System :: OS Independent
Requires-Python: >=3.6
License-File: LICENSE
Requires-Dist: fuzzysearch
Requires-Dist: prettytable
